kolla_kubernetes/__init__.py
kolla_kubernetes/app.py
kolla_kubernetes/exception.py
kolla_kubernetes/kube_service_status.py
kolla_kubernetes/pathfinder.py
kolla_kubernetes/service_resources.py
kolla_kubernetes/utils.py
kolla_kubernetes/version.py
kolla_kubernetes/commands/__init__.py
kolla_kubernetes/commands/base_command.py
kolla_kubernetes/commands/cmd_resource.py
kolla_kubernetes/commands/cmd_service.py
kolla_kubernetes/commands/genpwd.py
kolla_kubernetes/tests/__init__.py
kolla_kubernetes/tests/base.py
kolla_kubernetes/tests/test_helm_templates.py
kolla_kubernetes/tests/test_pathfinder.py
kolla_kubernetes/tests/test_templates.py
kolla_kubernetes/tests/test_utils.py
kolla_kubernetes-0.6.0.data/data/share/kolla-kubernetes/etc_examples/kolla-kubernetes/kolla-kubernetes.yml
kolla_kubernetes-0.6.0.data/data/share/kolla-kubernetes/etc_examples/kolla-kubernetes/service_resources.yml
kolla_kubernetes-0.6.0.data/data/share/kolla-kubernetes/services/WARNING
kolla_kubernetes-0.6.0.data/data/share/kolla-kubernetes/services/ceph/ceph-admin-pod.yml.j2
kolla_kubernetes-0.6.0.data/data/share/kolla-kubernetes/services/ceph/ceph-bootstrap-initial-mon.yml.j2
kolla_kubernetes-0.6.0.data/data/share/kolla-kubernetes/services/ceph/ceph-bootstrap-osd.yml.j2
kolla_kubernetes-0.6.0.data/data/share/kolla-kubernetes/services/ceph/ceph-mon-pod.yml.j2
kolla_kubernetes-0.6.0.data/data/share/kolla-kubernetes/services/ceph/ceph-osd-pod.yml.j2
kolla_kubernetes-0.6.0.data/data/share/kolla-kubernetes/services/ceph/ceph-rbd-pod.yml.j2
kolla_kubernetes-0.6.0.data/data/share/kolla-kubernetes/services/ceph/ceph-secret.yml.j2
kolla_kubernetes-0.6.0.data/data/share/kolla-kubernetes/services/common/api-haproxy-configmap.yml.j2
kolla_kubernetes-0.6.0.data/data/share/kolla-kubernetes/services/common/common-create-keystone-endpoint.yml.j2
kolla_kubernetes-0.6.0.data/data/share/kolla-kubernetes/services/common/common-create-keystone-user.yml.j2
kolla_kubernetes-0.6.0.dist-info/DESCRIPTION.rst
kolla_kubernetes-0.6.0.dist-info/METADATA
kolla_kubernetes-0.6.0.dist-info/RECORD
kolla_kubernetes-0.6.0.dist-info/WHEEL
kolla_kubernetes-0.6.0.dist-info/entry_points.txt
kolla_kubernetes-0.6.0.dist-info/metadata.json
kolla_kubernetes-0.6.0.dist-info/pbr.json
kolla_kubernetes-0.6.0.dist-info/top_level.txt
