Metadata-Version: 2.0
Name: kolla-kubernetes
Version: 0.6.0
Summary: Kubernetes deployment of the Kolla containers
Home-page: http://docs.openstack.org/developer/kolla-kubernetes
Author: OpenStack
Author-email: openstack-dev@lists.openstack.org
License: UNKNOWN
Platform: UNKNOWN
Classifier: Environment :: OpenStack
Classifier: Intended Audience :: Information Technology
Classifier: Intended Audience :: System Administrators
Classifier: License :: OSI Approved :: Apache Software License
Classifier: Operating System :: POSIX :: Linux
Classifier: Programming Language :: Python
Classifier: Programming Language :: Python :: 2
Classifier: Programming Language :: Python :: 2.7
Classifier: Programming Language :: Python :: 3
Classifier: Programming Language :: Python :: 3.4
Requires-Dist: Jinja2 (!=2.9.1,>=2.8,!=2.9.0,!=2.9.4,!=2.9.3,!=2.9.2)
Requires-Dist: PyYAML (>=3.10.0)
Requires-Dist: cliff (>=2.3.0)
Requires-Dist: kubernetes (>=1.0.0b1)
Requires-Dist: oslo.config (>=3.22.0)
Requires-Dist: oslo.log (>=3.22.0)
Requires-Dist: oslo.utils (>=3.20.0)
Requires-Dist: pbr (>=2.0.0,!=2.1.0)
Requires-Dist: six (>=1.9.0)
